{
    "action": [
        {
            "action_type": "SET_VARIABLE", 
            "args_list": [
                {
                    "arg_type": 100030, 
                    "args_list": [
                        {
                            "__tuple__": true, 
                            "items": [
                                "TABLE", 
                                "rsrcInfo", 
                                "local"
                            ]
                        }
                    ], 
                    "sub_type": 1
                }, 
                {
                    "arg_type": 100011, 
                    "args_list": [
                        {
                            "arg_type": 100025, 
                            "args_list": [
                                1
                            ], 
                            "sub_type": 1
                        }, 
                        {
                            "arg_type": 100247, 
                            "args_list": [
                                7
                            ], 
                            "sub_type": 1
                        }
                    ], 
                    "sub_type": "GET_PLAYER_SAVE_DATA_TABLE_VALUE"
                }
            ], 
            "bp": false, 
            "element_id": 1151443077000008, 
            "enable": true
        }, 
        {
            "action_type": "SET_VARIABLE", 
            "args_list": [
                {
                    "arg_type": 100030, 
                    "args_list": [
                        {
                            "__tuple__": true, 
                            "items": [
                                "TABLE", 
                                "shopMat", 
                                "local"
                            ]
                        }
                    ], 
                    "sub_type": 1
                }, 
                {
                    "arg_type": 100011, 
                    "args_list": [
                        "5f9f8e3b-a4ca-4c81-9e16-26624c00c3a3"
                    ], 
                    "sub_type": 1
                }
            ], 
            "bp": false, 
            "element_id": 1151443077000002, 
            "enable": true
        }, 
        {
            "action_type": "SET_VARIABLE", 
            "args_list": [
                {
                    "arg_type": 100030, 
                    "args_list": [
                        {
                            "__tuple__": true, 
                            "items": [
                                "INTEGER", 
                                "length_rsrcInfo", 
                                "local"
                            ]
                        }
                    ], 
                    "sub_type": 1
                }, 
                {
                    "arg_type": 100002, 
                    "args_list": [
                        {
                            "arg_type": 100011, 
                            "args_list": [
                                {
                                    "__tuple__": true, 
                                    "items": [
                                        "TABLE", 
                                        "rsrcInfo", 
                                        "local"
                                    ]
                                }
                            ], 
                            "sub_type": "VARIABLE"
                        }
                    ], 
                    "sub_type": "GET_TABLE_LENGTH"
                }
            ], 
            "bp": false, 
            "element_id": 1151443077000010, 
            "enable": true
        }, 
        {
            "action_type": "SET_VARIABLE", 
            "args_list": [
                {
                    "arg_type": 100030, 
                    "args_list": [
                        {
                            "__tuple__": true, 
                            "items": [
                                "INTEGER", 
                                "length_shopMat", 
                                "local"
                            ]
                        }
                    ], 
                    "sub_type": 1
                }, 
                {
                    "arg_type": 100002, 
                    "args_list": [
                        {
                            "arg_type": 100011, 
                            "args_list": [
                                {
                                    "__tuple__": true, 
                                    "items": [
                                        "TABLE", 
                                        "shopMat", 
                                        "local"
                                    ]
                                }
                            ], 
                            "sub_type": "VARIABLE"
                        }
                    ], 
                    "sub_type": "GET_TABLE_LENGTH"
                }
            ], 
            "bp": false, 
            "element_id": 1151443077000013, 
            "enable": true
        }, 
        {
            "action_type": "SET_VARIABLE", 
            "args_list": [
                {
                    "arg_type": 100030, 
                    "args_list": [
                        {
                            "__tuple__": true, 
                            "items": [
                                "INTEGER", 
                                "i", 
                                "local"
                            ]
                        }
                    ], 
                    "sub_type": 1
                }, 
                {
                    "arg_type": 100002, 
                    "args_list": [
                        1
                    ], 
                    "sub_type": 1
                }
            ], 
            "bp": false, 
            "element_id": 1151443077000029, 
            "enable": true
        }, 
        {
            "action_type": "ITER_UI_COMP_DO", 
            "args_list": [
                {
                    "arg_type": 100025, 
                    "args_list": [
                        1
                    ], 
                    "sub_type": 1
                }, 
                {
                    "arg_type": 100070, 
                    "args_list": [
                        "ffb74e53-434e-4172-86a0-fe9f0e5e4a9d"
                    ], 
                    "sub_type": 1
                }, 
                {
                    "arg_type": 100022, 
                    "args_list": [
                        {
                            "action_type": "SET_VARIABLE", 
                            "args_list": [
                                {
                                    "arg_type": 100030, 
                                    "args_list": [
                                        {
                                            "__tuple__": true, 
                                            "items": [
                                                "TEXTURE", 
                                                "matAvator", 
                                                "local"
                                            ]
                                        }
                                    ], 
                                    "sub_type": 1
                                }, 
                                {
                                    "arg_type": 100115, 
                                    "args_list": [
                                        {
                                            "arg_type": 100032, 
                                            "args_list": [
                                                {
                                                    "arg_type": 100011, 
                                                    "args_list": [
                                                        {
                                                            "__tuple__": true, 
                                                            "items": [
                                                                "TABLE", 
                                                                "shopMat", 
                                                                "local"
                                                            ]
                                                        }
                                                    ], 
                                                    "sub_type": "VARIABLE"
                                                }, 
                                                {
                                                    "arg_type": 100002, 
                                                    "args_list": [
                                                        {
                                                            "__tuple__": true, 
                                                            "items": [
                                                                "INTEGER", 
                                                                "i", 
                                                                "local"
                                                            ]
                                                        }
                                                    ], 
                                                    "sub_type": 6
                                                }, 
                                                {
                                                    "arg_type": 100003, 
                                                    "args_list": [
                                                        "material"
                                                    ], 
                                                    "sub_type": 1
                                                }
                                            ], 
                                            "sub_type": "GET_ITEM_NAME_TABLE_VAR_ND"
                                        }
                                    ], 
                                    "sub_type": "GET_ICON_BY_ITEM_TYPE"
                                }
                            ], 
                            "bp": false, 
                            "element_id": 1151443077000045, 
                            "enable": true
                        }, 
                        {
                            "action_type": "SET_UI_COMP_IMAGE_NEW", 
                            "args_list": [
                                {
                                    "arg_type": 100025, 
                                    "args_list": [
                                        1
                                    ], 
                                    "sub_type": 1
                                }, 
                                {
                                    "arg_type": 100070, 
                                    "args_list": [
                                        {
                                            "arg_type": 100025, 
                                            "args_list": [
                                                1
                                            ], 
                                            "sub_type": 1
                                        }, 
                                        {
                                            "arg_type": 100070, 
                                            "args_list": [], 
                                            "sub_type": "FOR_EACH_UI_COMP"
                                        }, 
                                        {
                                            "arg_type": 100003, 
                                            "args_list": [
                                                "avator"
                                            ], 
                                            "sub_type": 1
                                        }
                                    ], 
                                    "sub_type": "GET_UI_COMP_BY_PATH"
                                }, 
                                {
                                    "arg_type": 100115, 
                                    "args_list": [
                                        {
                                            "__tuple__": true, 
                                            "items": [
                                                "TEXTURE", 
                                                "matAvator", 
                                                "local"
                                            ]
                                        }
                                    ], 
                                    "sub_type": 2
                                }
                            ], 
                            "bp": false, 
                            "element_id": 1151443077000064, 
                            "enable": true
                        }, 
                        {
                            "action_type": "SET_VARIABLE", 
                            "args_list": [
                                {
                                    "arg_type": 100030, 
                                    "args_list": [
                                        {
                                            "__tuple__": true, 
                                            "items": [
                                                "STRING", 
                                                "click", 
                                                "local"
                                            ]
                                        }
                                    ], 
                                    "sub_type": 1
                                }, 
                                {
                                    "arg_type": 100003, 
                                    "args_list": [
                                        {
                                            "arg_type": 100003, 
                                            "args_list": [
                                                "click_choose_shopmat_"
                                            ], 
                                            "sub_type": 1
                                        }, 
                                        {
                                            "arg_type": 100003, 
                                            "args_list": [
                                                {
                                                    "arg_type": 100002, 
                                                    "args_list": [
                                                        {
                                                            "__tuple__": true, 
                                                            "items": [
                                                                "INTEGER", 
                                                                "i", 
                                                                "local"
                                                            ]
                                                        }
                                                    ], 
                                                    "sub_type": 6
                                                }
                                            ], 
                                            "sub_type": "ANY_VAR_TO_STR"
                                        }
                                    ], 
                                    "op_arg": [
                                        null, 
                                        null, 
                                        null, 
                                        null, 
                                        null, 
                                        null, 
                                        null, 
                                        null
                                    ], 
                                    "op_arg_enable": [
                                        false, 
                                        false, 
                                        false, 
                                        false, 
                                        false, 
                                        false, 
                                        false, 
                                        false
                                    ], 
                                    "sub_type": "STR_JOIN"
                                }
                            ], 
                            "bp": false, 
                            "element_id": 1151443077000136, 
                            "enable": true
                        }, 
                        {
                            "action_type": "CREATE_UI_COMP_EVENT_EX_EX", 
                            "args_list": [
                                {
                                    "arg_type": 100070, 
                                    "args_list": [], 
                                    "sub_type": "FOR_EACH_UI_COMP"
                                }, 
                                {
                                    "arg_type": 100072, 
                                    "args_list": [
                                        30
                                    ], 
                                    "sub_type": 1
                                }, 
                                {
                                    "arg_type": 100003, 
                                    "args_list": [
                                        [
                                            "STRING", 
                                            "click", 
                                            "local"
                                        ]
                                    ], 
                                    "sub_type": 2
                                }
                            ], 
                            "bp": false, 
                            "element_id": 2146480253973797, 
                            "enable": true, 
                            "op_arg": [
                                null
                            ], 
                            "op_arg_enable": [
                                false
                            ]
                        }, 
                        1017831560, 
                        {
                            "action_type": "SET_VARIABLE", 
                            "args_list": [
                                {
                                    "arg_type": 100030, 
                                    "args_list": [
                                        {
                                            "__tuple__": true, 
                                            "items": [
                                                "INTEGER", 
                                                "i", 
                                                "local"
                                            ]
                                        }
                                    ], 
                                    "sub_type": 1
                                }, 
                                {
                                    "arg_type": 100002, 
                                    "args_list": [
                                        {
                                            "arg_type": 100002, 
                                            "args_list": [
                                                {
                                                    "__tuple__": true, 
                                                    "items": [
                                                        "INTEGER", 
                                                        "i", 
                                                        "local"
                                                    ]
                                                }
                                            ], 
                                            "sub_type": 6
                                        }
                                    ], 
                                    "sub_type": "INT_PLUS_ONE"
                                }
                            ], 
                            "bp": false, 
                            "element_id": 1151443077000126, 
                            "enable": true
                        }
                    ], 
                    "sub_type": 1
                }
            ], 
            "bp": false, 
            "element_id": 1151443077000036, 
            "enable": true
        }
    ], 
    "call_enabled": true, 
    "condition": [], 
    "enabled": true, 
    "event": [], 
    "func_category": "t_function", 
    "func_comment": "", 
    "func_des": "更新商店材料", 
    "func_id": "5feda48024cd11efbf12b025aa5232dc", 
    "func_name": "ShopMaterial", 
    "group_id": "NerfQCSqEe+N6rAlqlIy3D", 
    "is_func": true, 
    "is_official_func": false, 
    "p_trigger_id": null, 
    "sub_trigger": {
        "1017831560": {
            "action": [
                {
                    "action_type": "SET_VARIABLE", 
                    "args_list": [
                        {
                            "arg_type": 100030, 
                            "args_list": [
                                {
                                    "__tuple__": true, 
                                    "items": [
                                        "ITEM_NAME", 
                                        "SHOP_MATERIAL"
                                    ]
                                }
                            ], 
                            "sub_type": 1
                        }, 
                        {
                            "arg_type": 100032, 
                            "args_list": [
                                {
                                    "arg_type": 100011, 
                                    "args_list": [
                                        {
                                            "__tuple__": true, 
                                            "items": [
                                                "TABLE", 
                                                "shopMat", 
                                                "local"
                                            ]
                                        }
                                    ], 
                                    "sub_type": "VARIABLE"
                                }, 
                                {
                                    "arg_type": 100002, 
                                    "args_list": [
                                        {
                                            "__tuple__": true, 
                                            "items": [
                                                "INTEGER", 
                                                "i", 
                                                "local"
                                            ]
                                        }
                                    ], 
                                    "sub_type": 6
                                }, 
                                {
                                    "arg_type": 100003, 
                                    "args_list": [
                                        "material"
                                    ], 
                                    "sub_type": 1
                                }
                            ], 
                            "sub_type": "GET_ITEM_NAME_TABLE_VAR_ND"
                        }
                    ], 
                    "bp": false, 
                    "element_id": 1017831560000178, 
                    "enable": true
                }, 
                {
                    "action_type": "SET_UI_COMP_VISIBLE", 
                    "args_list": [
                        {
                            "arg_type": 100025, 
                            "args_list": [
                                1
                            ], 
                            "sub_type": 1
                        }, 
                        {
                            "arg_type": 100001, 
                            "args_list": [
                                true
                            ], 
                            "sub_type": 1
                        }, 
                        {
                            "arg_type": 100070, 
                            "args_list": [
                                "d5a91783-907a-4634-a692-d30df197128d"
                            ], 
                            "sub_type": 1
                        }
                    ], 
                    "bp": false, 
                    "element_id": 791433342000528, 
                    "enable": true
                }, 
                {
                    "action_type": "SET_UI_COMP_VISIBLE", 
                    "args_list": [
                        {
                            "arg_type": 100025, 
                            "args_list": [
                                1
                            ], 
                            "sub_type": 1
                        }, 
                        {
                            "arg_type": 100001, 
                            "args_list": [
                                true
                            ], 
                            "sub_type": 1
                        }, 
                        {
                            "arg_type": 100070, 
                            "args_list": [
                                "eb8e5525-62b4-4931-a5ce-cbc77bd80c08"
                            ], 
                            "sub_type": 1
                        }
                    ], 
                    "bp": false, 
                    "element_id": 1110708358000016, 
                    "enable": true
                }, 
                {
                    "action_type": "SET_UI_COMP_IMAGE_NEW", 
                    "args_list": [
                        {
                            "arg_type": 100025, 
                            "args_list": [
                                1
                            ], 
                            "sub_type": 1
                        }, 
                        {
                            "arg_type": 100070, 
                            "args_list": [
                                "5b891988-3203-496b-8e29-26a187cd67a9"
                            ], 
                            "sub_type": 1
                        }, 
                        {
                            "arg_type": 100115, 
                            "args_list": [
                                {
                                    "__tuple__": true, 
                                    "items": [
                                        "TEXTURE", 
                                        "matAvator", 
                                        "local"
                                    ]
                                }
                            ], 
                            "sub_type": 2
                        }
                    ], 
                    "bp": false, 
                    "element_id": 1017831560000098, 
                    "enable": true
                }, 
                {
                    "action_type": "SET_VARIABLE", 
                    "args_list": [
                        {
                            "arg_type": 100030, 
                            "args_list": [
                                {
                                    "__tuple__": true, 
                                    "items": [
                                        "STRING", 
                                        "matName", 
                                        "local"
                                    ]
                                }
                            ], 
                            "sub_type": 1
                        }, 
                        {
                            "arg_type": 100003, 
                            "args_list": [
                                {
                                    "arg_type": 100032, 
                                    "args_list": [
                                        {
                                            "arg_type": 100011, 
                                            "args_list": [
                                                {
                                                    "__tuple__": true, 
                                                    "items": [
                                                        "TABLE", 
                                                        "shopMat", 
                                                        "local"
                                                    ]
                                                }
                                            ], 
                                            "sub_type": "VARIABLE"
                                        }, 
                                        {
                                            "arg_type": 100002, 
                                            "args_list": [
                                                {
                                                    "__tuple__": true, 
                                                    "items": [
                                                        "INTEGER", 
                                                        "i", 
                                                        "local"
                                                    ]
                                                }
                                            ], 
                                            "sub_type": 6
                                        }, 
                                        {
                                            "arg_type": 100003, 
                                            "args_list": [
                                                "material"
                                            ], 
                                            "sub_type": 1
                                        }
                                    ], 
                                    "sub_type": "GET_ITEM_NAME_TABLE_VAR_ND"
                                }
                            ], 
                            "sub_type": "GET_ITEM_CONF_NAME"
                        }
                    ], 
                    "bp": false, 
                    "element_id": 1151443077000081, 
                    "enable": true
                }, 
                {
                    "action_type": "SET_UI_COMP_TEXT", 
                    "args_list": [
                        {
                            "arg_type": 100025, 
                            "args_list": [
                                1
                            ], 
                            "sub_type": 1
                        }, 
                        {
                            "arg_type": 100070, 
                            "args_list": [
                                "c2f4ce06-efc0-49d6-ad1f-ac988208f975"
                            ], 
                            "sub_type": 1
                        }, 
                        {
                            "arg_type": 100003, 
                            "args_list": [
                                {
                                    "__tuple__": true, 
                                    "items": [
                                        "STRING", 
                                        "matName", 
                                        "local"
                                    ]
                                }
                            ], 
                            "sub_type": 2
                        }
                    ], 
                    "bp": false, 
                    "element_id": 1151443077000116, 
                    "enable": true
                }, 
                {
                    "action_type": "SET_VARIABLE", 
                    "args_list": [
                        {
                            "arg_type": 100030, 
                            "args_list": [
                                {
                                    "__tuple__": true, 
                                    "items": [
                                        "STRING", 
                                        "matDesc", 
                                        "local"
                                    ]
                                }
                            ], 
                            "sub_type": 1
                        }, 
                        {
                            "arg_type": 100003, 
                            "args_list": [
                                {
                                    "arg_type": 100032, 
                                    "args_list": [
                                        {
                                            "arg_type": 100011, 
                                            "args_list": [
                                                {
                                                    "__tuple__": true, 
                                                    "items": [
                                                        "TABLE", 
                                                        "shopMat", 
                                                        "local"
                                                    ]
                                                }
                                            ], 
                                            "sub_type": "VARIABLE"
                                        }, 
                                        {
                                            "arg_type": 100002, 
                                            "args_list": [
                                                {
                                                    "__tuple__": true, 
                                                    "items": [
                                                        "INTEGER", 
                                                        "i", 
                                                        "local"
                                                    ]
                                                }
                                            ], 
                                            "sub_type": 6
                                        }, 
                                        {
                                            "arg_type": 100003, 
                                            "args_list": [
                                                "material"
                                            ], 
                                            "sub_type": 1
                                        }
                                    ], 
                                    "sub_type": "GET_ITEM_NAME_TABLE_VAR_ND"
                                }
                            ], 
                            "sub_type": "GET_DES_ID_BY_ITEM_TYPE"
                        }
                    ], 
                    "bp": false, 
                    "element_id": 1151443077000091, 
                    "enable": true
                }, 
                {
                    "action_type": "SET_UI_COMP_TEXT", 
                    "args_list": [
                        {
                            "arg_type": 100025, 
                            "args_list": [
                                1
                            ], 
                            "sub_type": 1
                        }, 
                        {
                            "arg_type": 100070, 
                            "args_list": [
                                "730a100b-6e36-4f62-8c2a-1d1ec10d57f6"
                            ], 
                            "sub_type": 1
                        }, 
                        {
                            "arg_type": 100003, 
                            "args_list": [
                                {
                                    "__tuple__": true, 
                                    "items": [
                                        "STRING", 
                                        "matDesc", 
                                        "local"
                                    ]
                                }
                            ], 
                            "sub_type": 2
                        }
                    ], 
                    "bp": false, 
                    "element_id": 1017831560000017, 
                    "enable": true
                }, 
                {
                    "action_type": "SET_VARIABLE", 
                    "args_list": [
                        {
                            "arg_type": 100030, 
                            "args_list": [
                                {
                                    "__tuple__": true, 
                                    "items": [
                                        "INTEGER", 
                                        "SHOP_NUM"
                                    ]
                                }
                            ], 
                            "sub_type": 1
                        }, 
                        {
                            "arg_type": 100002, 
                            "args_list": [
                                {
                                    "arg_type": 100011, 
                                    "args_list": [
                                        {
                                            "__tuple__": true, 
                                            "items": [
                                                "TABLE", 
                                                "shopMat", 
                                                "local"
                                            ]
                                        }
                                    ], 
                                    "sub_type": "VARIABLE"
                                }, 
                                {
                                    "arg_type": 100002, 
                                    "args_list": [
                                        {
                                            "__tuple__": true, 
                                            "items": [
                                                "INTEGER", 
                                                "i", 
                                                "local"
                                            ]
                                        }
                                    ], 
                                    "sub_type": 6
                                }, 
                                {
                                    "arg_type": 100003, 
                                    "args_list": [
                                        "num"
                                    ], 
                                    "sub_type": 1
                                }
                            ], 
                            "sub_type": "GET_INTEGER_TABLE_VAR_ND"
                        }
                    ], 
                    "bp": false, 
                    "element_id": 1017831560000152, 
                    "enable": true
                }, 
                {
                    "action_type": "SET_VARIABLE", 
                    "args_list": [
                        {
                            "arg_type": 100030, 
                            "args_list": [
                                {
                                    "__tuple__": true, 
                                    "items": [
                                        "STRING", 
                                        "num_str", 
                                        "local"
                                    ]
                                }
                            ], 
                            "sub_type": 1
                        }, 
                        {
                            "arg_type": 100003, 
                            "args_list": [
                                {
                                    "arg_type": 100002, 
                                    "args_list": [
                                        {
                                            "__tuple__": true, 
                                            "items": [
                                                "INTEGER", 
                                                "SHOP_NUM"
                                            ]
                                        }
                                    ], 
                                    "sub_type": 6
                                }
                            ], 
                            "sub_type": "ANY_VAR_TO_STR"
                        }
                    ], 
                    "bp": false, 
                    "element_id": 1017831560000159, 
                    "enable": true
                }, 
                {
                    "action_type": "SET_UI_COMP_TEXT", 
                    "args_list": [
                        {
                            "arg_type": 100025, 
                            "args_list": [
                                1
                            ], 
                            "sub_type": 1
                        }, 
                        {
                            "arg_type": 100070, 
                            "args_list": [
                                "05e07cb6-daa4-4e14-9273-16b23170948a"
                            ], 
                            "sub_type": 1
                        }, 
                        {
                            "arg_type": 100003, 
                            "args_list": [
                                {
                                    "__tuple__": true, 
                                    "items": [
                                        "STRING", 
                                        "num_str", 
                                        "local"
                                    ]
                                }
                            ], 
                            "sub_type": 2
                        }
                    ], 
                    "bp": false, 
                    "element_id": 1017831560000166, 
                    "enable": true
                }, 
                {
                    "action_type": "SET_VARIABLE", 
                    "args_list": [
                        {
                            "arg_type": 100030, 
                            "args_list": [
                                {
                                    "__tuple__": true, 
                                    "items": [
                                        "ITEM_NAME", 
                                        "SHOP_TYPE"
                                    ]
                                }
                            ], 
                            "sub_type": 1
                        }, 
                        {
                            "arg_type": 100032, 
                            "args_list": [
                                {
                                    "arg_type": 100011, 
                                    "args_list": [
                                        {
                                            "__tuple__": true, 
                                            "items": [
                                                "TABLE", 
                                                "shopMat", 
                                                "local"
                                            ]
                                        }
                                    ], 
                                    "sub_type": "VARIABLE"
                                }, 
                                {
                                    "arg_type": 100002, 
                                    "args_list": [
                                        {
                                            "__tuple__": true, 
                                            "items": [
                                                "INTEGER", 
                                                "i", 
                                                "local"
                                            ]
                                        }
                                    ], 
                                    "sub_type": 6
                                }, 
                                {
                                    "arg_type": 100003, 
                                    "args_list": [
                                        "type"
                                    ], 
                                    "sub_type": 1
                                }
                            ], 
                            "sub_type": "GET_ITEM_NAME_TABLE_VAR_ND"
                        }
                    ], 
                    "bp": false, 
                    "element_id": 1017831560000045, 
                    "enable": true
                }, 
                {
                    "action_type": "PRINT_MESSAGE_ACTION_TO_DIALOG", 
                    "args_list": [
                        {
                            "arg_type": 100175, 
                            "args_list": [
                                3
                            ], 
                            "sub_type": 1
                        }, 
                        {
                            "arg_type": 100003, 
                            "args_list": [
                                {
                                    "arg_type": 100032, 
                                    "args_list": [
                                        {
                                            "__tuple__": true, 
                                            "items": [
                                                "ITEM_NAME", 
                                                "SHOP_TYPE"
                                            ]
                                        }
                                    ], 
                                    "sub_type": 2
                                }
                            ], 
                            "sub_type": "ANY_VAR_TO_STR"
                        }
                    ], 
                    "bp": false, 
                    "element_id": 1017831560000183, 
                    "enable": false
                }, 
                {
                    "action_type": "SET_VARIABLE", 
                    "args_list": [
                        {
                            "arg_type": 100030, 
                            "args_list": [
                                [
                                    "TEXTURE", 
                                    "priceIcon", 
                                    "local"
                                ]
                            ], 
                            "sub_type": 1
                        }, 
                        {
                            "arg_type": 100115, 
                            "args_list": [
                                {
                                    "arg_type": 100032, 
                                    "args_list": [
                                        {
                                            "__tuple__": true, 
                                            "items": [
                                                "ITEM_NAME", 
                                                "SHOP_TYPE"
                                            ]
                                        }
                                    ], 
                                    "sub_type": 2
                                }
                            ], 
                            "sub_type": "GET_ICON_BY_ITEM_TYPE"
                        }
                    ], 
                    "bp": false, 
                    "element_id": 1017831560000079, 
                    "enable": true
                }, 
                {
                    "action_type": "SET_UI_COMP_IMAGE_NEW", 
                    "args_list": [
                        {
                            "arg_type": 100025, 
                            "args_list": [
                                1
                            ], 
                            "sub_type": 1
                        }, 
                        {
                            "arg_type": 100070, 
                            "args_list": [
                                "e9ee0c28-f838-43e5-b441-f45b31b8da14"
                            ], 
                            "sub_type": 1
                        }, 
                        {
                            "arg_type": 100115, 
                            "args_list": [
                                [
                                    "TEXTURE", 
                                    "priceIcon", 
                                    "local"
                                ]
                            ], 
                            "sub_type": 2
                        }
                    ], 
                    "bp": false, 
                    "element_id": 1017831560000088, 
                    "enable": true
                }, 
                {
                    "action_type": "SET_VARIABLE", 
                    "args_list": [
                        {
                            "arg_type": 100030, 
                            "args_list": [
                                {
                                    "__tuple__": true, 
                                    "items": [
                                        "INTEGER", 
                                        "SHOP_PRICE"
                                    ]
                                }
                            ], 
                            "sub_type": 1
                        }, 
                        {
                            "arg_type": 100002, 
                            "args_list": [
                                {
                                    "arg_type": 100011, 
                                    "args_list": [
                                        {
                                            "__tuple__": true, 
                                            "items": [
                                                "TABLE", 
                                                "shopMat", 
                                                "local"
                                            ]
                                        }
                                    ], 
                                    "sub_type": "VARIABLE"
                                }, 
                                {
                                    "arg_type": 100002, 
                                    "args_list": [
                                        {
                                            "__tuple__": true, 
                                            "items": [
                                                "INTEGER", 
                                                "i", 
                                                "local"
                                            ]
                                        }
                                    ], 
                                    "sub_type": 6
                                }, 
                                {
                                    "arg_type": 100003, 
                                    "args_list": [
                                        "price"
                                    ], 
                                    "sub_type": 1
                                }
                            ], 
                            "sub_type": "GET_INTEGER_TABLE_VAR_ND"
                        }
                    ], 
                    "bp": false, 
                    "element_id": 1017831560000110, 
                    "enable": true
                }, 
                {
                    "action_type": "SET_VARIABLE", 
                    "args_list": [
                        {
                            "arg_type": 100030, 
                            "args_list": [
                                {
                                    "__tuple__": true, 
                                    "items": [
                                        "STRING", 
                                        "price_str", 
                                        "local"
                                    ]
                                }
                            ], 
                            "sub_type": 1
                        }, 
                        {
                            "arg_type": 100003, 
                            "args_list": [
                                {
                                    "arg_type": 100002, 
                                    "args_list": [
                                        {
                                            "__tuple__": true, 
                                            "items": [
                                                "INTEGER", 
                                                "SHOP_PRICE"
                                            ]
                                        }
                                    ], 
                                    "sub_type": 6
                                }
                            ], 
                            "sub_type": "ANY_VAR_TO_STR"
                        }
                    ], 
                    "bp": false, 
                    "element_id": 1017831560000126, 
                    "enable": true
                }, 
                {
                    "action_type": "SET_UI_COMP_TEXT", 
                    "args_list": [
                        {
                            "arg_type": 100025, 
                            "args_list": [
                                1
                            ], 
                            "sub_type": 1
                        }, 
                        {
                            "arg_type": 100070, 
                            "args_list": [
                                "ea200e8b-c8df-43ed-b8c7-534225882c46"
                            ], 
                            "sub_type": 1
                        }, 
                        {
                            "arg_type": 100003, 
                            "args_list": [
                                {
                                    "__tuple__": true, 
                                    "items": [
                                        "STRING", 
                                        "price_str", 
                                        "local"
                                    ]
                                }
                            ], 
                            "sub_type": 2
                        }
                    ], 
                    "bp": false, 
                    "element_id": 1017831560000124, 
                    "enable": true
                }
            ], 
            "call_enabled": true, 
            "condition": [], 
            "enabled": false, 
            "event": [
                {
                    "args_list": [
                        {
                            "arg_type": 100067, 
                            "args_list": [
                                {
                                    "arg_type": 100003, 
                                    "args_list": [
                                        {
                                            "__tuple__": true, 
                                            "items": [
                                                "STRING", 
                                                "click", 
                                                "local"
                                            ]
                                        }
                                    ], 
                                    "sub_type": 2
                                }
                            ], 
                            "sub_type": "STR_TO_UI_EVENT"
                        }
                    ], 
                    "element_id": 1017831560000004, 
                    "enable": true, 
                    "event_type": "TRIGGER_COMPONENT_EVENT"
                }
            ], 
            "group_id": 0, 
            "is_conf": true, 
            "p_trigger_id": 1151443077, 
            "trigger_id": 1017831560, 
            "trigger_name": "on_click_shopmat", 
            "valid": true
        }
    }, 
    "trigger_id": 1151443077, 
    "trigger_name": "ShopMaterial", 
    "valid": true
}