{
    "action": [
        {
            "action_type": "SET_UI_COMP_VISIBLE", 
            "args_list": [
                {
                    "arg_type": 100025, 
                    "args_list": [
                        1
                    ], 
                    "sub_type": 1
                }, 
                {
                    "arg_type": 100001, 
                    "args_list": [
                        false
                    ], 
                    "sub_type": 1
                }, 
                {
                    "arg_type": 100070, 
                    "args_list": [
                        "c5c09f12-f3d7-4b57-a18e-ceff75a73d80"
                    ], 
                    "sub_type": 1
                }
            ], 
            "bp": false, 
            "element_id": 1751359698000024, 
            "enable": true
        }, 
        {
            "action_type": "SET_UI_COMP_VISIBLE", 
            "args_list": [
                {
                    "arg_type": 100025, 
                    "args_list": [
                        1
                    ], 
                    "sub_type": 1
                }, 
                {
                    "arg_type": 100001, 
                    "args_list": [
                        true
                    ], 
                    "sub_type": 1
                }, 
                {
                    "arg_type": 100070, 
                    "args_list": [
                        "2690b161-bba0-443e-b883-bc68360d8eaf"
                    ], 
                    "sub_type": 1
                }
            ], 
            "bp": false, 
            "element_id": 1751359698000029, 
            "enable": true
        }
    ], 
    "call_enabled": true, 
    "condition": [
        {
            "args_list": [
                {
                    "arg_type": 100001, 
                    "args_list": [
                        {
                            "arg_type": 100025, 
                            "args_list": [
                                1
                            ], 
                            "sub_type": 1
                        }, 
                        {
                            "arg_type": 100233, 
                            "args_list": [
                                8
                            ], 
                            "sub_type": 1
                        }
                    ], 
                    "sub_type": "GET_PLAYER_SAVE_DATA_BOOL_VALUE"
                }, 
                {
                    "arg_type": 100035, 
                    "args_list": [
                        "=="
                    ], 
                    "sub_type": 1
                }, 
                {
                    "arg_type": 100001, 
                    "args_list": [
                        false
                    ], 
                    "sub_type": 1
                }
            ], 
            "condition_type": "BOOL_COMPARE", 
            "element_id": 1751359698000006, 
            "enable": true
        }
    ], 
    "enabled": true, 
    "event": [
        {
            "args_list": [], 
            "element_id": 1751359698000002, 
            "enable": true, 
            "event_type": "INIT_FINISHED"
        }
    ], 
    "group_id": "RfRV4TZ8Ee+oY7AlqlIy3M", 
    "p_trigger_id": null, 
    "trigger_id": 1751359698, 
    "trigger_name": "is_read_letter", 
    "valid": true, 
    "var_data": [
        {}, 
        {}, 
        []
    ]
}